{
  "openapi": "3.0.0",
  "paths": {
    "/auth/register": {
      "post": {
        "operationId": "AuthController_register",
        "parameters": [],
        "requestBody": {
          "required": true,
          "content": {
            "application/json": {
              "schema": {
                "$ref": "#/components/schemas/RegisterDto"
              }
            }
          }
        },
        "responses": {
          "201": {
            "description": ""
          }
        },
        "tags": [
          "auth"
        ]
      }
    },
    "/auth/login": {
      "post": {
        "operationId": "AuthController_login",
        "parameters": [],
        "requestBody": {
          "required": true,
          "content": {
            "application/json": {
              "schema": {
                "$ref": "#/components/schemas/LoginDto"
              }
            }
          }
        },
        "responses": {
          "201": {
            "description": ""
          }
        },
        "tags": [
          "auth"
        ]
      }
    },
    "/users/me": {
      "get": {
        "operationId": "UsersController_me",
        "parameters": [],
        "responses": {
          "200": {
            "description": ""
          }
        },
        "tags": [
          "users"
        ],
        "security": [
          {
            "access-token": []
          },
          {
            "access-token": []
          }
        ]
      }
    },
    "/users": {
      "get": {
        "operationId": "UsersController_list",
        "parameters": [],
        "responses": {
          "200": {
            "description": ""
          }
        },
        "tags": [
          "users"
        ],
        "security": [
          {
            "access-token": []
          },
          {
            "access-token": []
          }
        ]
      }
    },
    "/courses/published": {
      "get": {
        "operationId": "CoursesController_listPublished",
        "parameters": [],
        "responses": {
          "200": {
            "description": ""
          }
        },
        "tags": [
          "courses"
        ],
        "security": [
          {
            "access-token": []
          }
        ]
      }
    },
    "/courses/published/{id}": {
      "get": {
        "operationId": "CoursesController_getPublished",
        "parameters": [
          {
            "name": "id",
            "required": true,
            "in": "path",
            "schema": {
              "type": "string"
            }
          }
        ],
        "responses": {
          "200": {
            "description": ""
          }
        },
        "tags": [
          "courses"
        ],
        "security": [
          {
            "access-token": []
          }
        ]
      }
    },
    "/courses": {
      "get": {
        "operationId": "CoursesController_listAll",
        "parameters": [],
        "responses": {
          "200": {
            "description": ""
          }
        },
        "tags": [
          "courses"
        ],
        "security": [
          {
            "access-token": []
          },
          {
            "access-token": []
          }
        ]
      },
      "post": {
        "operationId": "CoursesController_create",
        "parameters": [],
        "requestBody": {
          "required": true,
          "content": {
            "application/json": {
              "schema": {
                "$ref": "#/components/schemas/CreateCourseDto"
              }
            }
          }
        },
        "responses": {
          "201": {
            "description": ""
          }
        },
        "tags": [
          "courses"
        ],
        "security": [
          {
            "access-token": []
          },
          {
            "access-token": []
          }
        ]
      }
    },
    "/courses/{id}/publish": {
      "patch": {
        "operationId": "CoursesController_publish",
        "parameters": [
          {
            "name": "id",
            "required": true,
            "in": "path",
            "schema": {
              "type": "string"
            }
          }
        ],
        "requestBody": {
          "required": true,
          "content": {
            "application/json": {
              "schema": {
                "$ref": "#/components/schemas/PublishCourseDto"
              }
            }
          }
        },
        "responses": {
          "200": {
            "description": ""
          }
        },
        "tags": [
          "courses"
        ],
        "security": [
          {
            "access-token": []
          },
          {
            "access-token": []
          }
        ]
      }
    },
    "/reports/users": {
      "get": {
        "operationId": "ReportsController_users",
        "parameters": [
          {
            "name": "to",
            "required": false,
            "in": "query",
            "description": "ISO date (e.g. 2026-02-14)",
            "schema": {}
          },
          {
            "name": "from",
            "required": false,
            "in": "query",
            "description": "ISO date (e.g. 2026-02-01)",
            "schema": {}
          },
          {
            "name": "role",
            "required": false,
            "in": "query",
            "schema": {
              "enum": [
                "ADMIN",
                "INSTRUCTOR",
                "STUDENT"
              ],
              "type": "string"
            }
          },
          {
            "name": "format",
            "required": false,
            "in": "query",
            "schema": {
              "enum": [
                "pdf",
                "csv",
                "xlsx",
                "doc",
                "docx"
              ],
              "type": "string"
            }
          }
        ],
        "responses": {
          "200": {
            "description": ""
          }
        },
        "tags": [
          "reports"
        ],
        "security": [
          {
            "access-token": []
          },
          {
            "access-token": []
          }
        ]
      }
    },
    "/reports/schedules": {
      "get": {
        "operationId": "ReportsController_listSchedules",
        "parameters": [],
        "responses": {
          "200": {
            "description": ""
          }
        },
        "tags": [
          "reports"
        ],
        "security": [
          {
            "access-token": []
          },
          {
            "access-token": []
          }
        ]
      },
      "post": {
        "operationId": "ReportsController_createSchedule",
        "parameters": [],
        "requestBody": {
          "required": true,
          "content": {
            "application/json": {
              "schema": {
                "$ref": "#/components/schemas/CreateScheduledReportDto"
              }
            }
          }
        },
        "responses": {
          "201": {
            "description": ""
          }
        },
        "tags": [
          "reports"
        ],
        "security": [
          {
            "access-token": []
          },
          {
            "access-token": []
          }
        ]
      }
    },
    "/reports/schedules/{id}": {
      "patch": {
        "operationId": "ReportsController_updateSchedule",
        "parameters": [
          {
            "name": "id",
            "required": true,
            "in": "path",
            "schema": {
              "type": "string"
            }
          }
        ],
        "requestBody": {
          "required": true,
          "content": {
            "application/json": {
              "schema": {
                "$ref": "#/components/schemas/UpdateScheduledReportDto"
              }
            }
          }
        },
        "responses": {
          "200": {
            "description": ""
          }
        },
        "tags": [
          "reports"
        ],
        "security": [
          {
            "access-token": []
          },
          {
            "access-token": []
          }
        ]
      }
    },
    "/reports/schedules/dispatch-due": {
      "post": {
        "operationId": "ReportsController_dispatchDue",
        "parameters": [],
        "responses": {
          "201": {
            "description": ""
          }
        },
        "tags": [
          "reports"
        ],
        "security": [
          {
            "access-token": []
          },
          {
            "access-token": []
          }
        ]
      }
    },
    "/courses/{courseId}/lessons": {
      "post": {
        "operationId": "LessonsController_create",
        "parameters": [
          {
            "name": "courseId",
            "required": true,
            "in": "path",
            "schema": {
              "type": "string"
            }
          }
        ],
        "requestBody": {
          "required": true,
          "content": {
            "application/json": {
              "schema": {
                "$ref": "#/components/schemas/CreateLessonDto"
              }
            }
          }
        },
        "responses": {
          "201": {
            "description": ""
          }
        },
        "tags": [
          "lessons"
        ],
        "security": [
          {
            "access-token": []
          }
        ]
      },
      "get": {
        "operationId": "LessonsController_list",
        "parameters": [
          {
            "name": "courseId",
            "required": true,
            "in": "path",
            "schema": {
              "type": "string"
            }
          }
        ],
        "responses": {
          "200": {
            "description": ""
          }
        },
        "tags": [
          "lessons"
        ],
        "security": [
          {
            "access-token": []
          }
        ]
      }
    },
    "/courses/{courseId}/lessons/{lessonId}": {
      "get": {
        "operationId": "LessonsController_get",
        "parameters": [
          {
            "name": "courseId",
            "required": true,
            "in": "path",
            "schema": {
              "type": "string"
            }
          },
          {
            "name": "lessonId",
            "required": true,
            "in": "path",
            "schema": {
              "type": "string"
            }
          }
        ],
        "responses": {
          "200": {
            "description": ""
          }
        },
        "tags": [
          "lessons"
        ],
        "security": [
          {
            "access-token": []
          }
        ]
      }
    },
    "/courses/{courseId}/enroll": {
      "post": {
        "operationId": "EnrollmentsController_enroll",
        "parameters": [
          {
            "name": "courseId",
            "required": true,
            "in": "path",
            "schema": {
              "type": "string"
            }
          }
        ],
        "responses": {
          "201": {
            "description": ""
          }
        },
        "tags": [
          "enrollments"
        ],
        "security": [
          {
            "access-token": []
          }
        ]
      }
    },
    "/me/enrollments": {
      "get": {
        "operationId": "EnrollmentsController_my",
        "parameters": [],
        "responses": {
          "200": {
            "description": ""
          }
        },
        "tags": [
          "enrollments"
        ],
        "security": [
          {
            "access-token": []
          }
        ]
      }
    },
    "/enrollments/{id}/complete": {
      "patch": {
        "operationId": "EnrollmentsController_complete",
        "parameters": [
          {
            "name": "id",
            "required": true,
            "in": "path",
            "schema": {
              "type": "string"
            }
          }
        ],
        "responses": {
          "200": {
            "description": ""
          }
        },
        "tags": [
          "enrollments"
        ],
        "security": [
          {
            "access-token": []
          }
        ]
      }
    },
    "/enrollments/{id}/refund": {
      "patch": {
        "operationId": "EnrollmentsController_refund",
        "parameters": [
          {
            "name": "id",
            "required": true,
            "in": "path",
            "schema": {
              "type": "string"
            }
          }
        ],
        "responses": {
          "200": {
            "description": ""
          }
        },
        "tags": [
          "enrollments"
        ],
        "security": [
          {
            "access-token": []
          }
        ]
      }
    },
    "/learning-plans": {
      "post": {
        "operationId": "LearningPlansController_create",
        "parameters": [],
        "requestBody": {
          "required": true,
          "content": {
            "application/json": {
              "schema": {
                "$ref": "#/components/schemas/CreateLearningPlanDto"
              }
            }
          }
        },
        "responses": {
          "201": {
            "description": ""
          }
        },
        "tags": [
          "learning-plans"
        ],
        "security": [
          {
            "access-token": []
          }
        ]
      },
      "get": {
        "operationId": "LearningPlansController_list",
        "parameters": [],
        "responses": {
          "200": {
            "description": ""
          }
        },
        "tags": [
          "learning-plans"
        ],
        "security": [
          {
            "access-token": []
          }
        ]
      }
    },
    "/learning-plans/{id}/courses": {
      "post": {
        "operationId": "LearningPlansController_addCourse",
        "parameters": [
          {
            "name": "id",
            "required": true,
            "in": "path",
            "schema": {
              "type": "string"
            }
          }
        ],
        "requestBody": {
          "required": true,
          "content": {
            "application/json": {
              "schema": {
                "$ref": "#/components/schemas/AddCourseToLearningPlanDto"
              }
            }
          }
        },
        "responses": {
          "201": {
            "description": ""
          }
        },
        "tags": [
          "learning-plans"
        ],
        "security": [
          {
            "access-token": []
          }
        ]
      }
    },
    "/learning-plans/{id}/assign": {
      "post": {
        "operationId": "LearningPlansController_assign",
        "parameters": [
          {
            "name": "id",
            "required": true,
            "in": "path",
            "schema": {
              "type": "string"
            }
          }
        ],
        "requestBody": {
          "required": true,
          "content": {
            "application/json": {
              "schema": {
                "$ref": "#/components/schemas/AssignLearningPlanDto"
              }
            }
          }
        },
        "responses": {
          "201": {
            "description": ""
          }
        },
        "tags": [
          "learning-plans"
        ],
        "security": [
          {
            "access-token": []
          }
        ]
      }
    },
    "/certifications/me": {
      "get": {
        "operationId": "CertificationsController_my",
        "parameters": [],
        "responses": {
          "200": {
            "description": ""
          }
        },
        "tags": [
          "certifications"
        ],
        "security": [
          {
            "access-token": []
          }
        ]
      }
    },
    "/certifications/issue": {
      "post": {
        "operationId": "CertificationsController_issue",
        "parameters": [],
        "requestBody": {
          "required": true,
          "content": {
            "application/json": {
              "schema": {
                "$ref": "#/components/schemas/IssueCertificationDto"
              }
            }
          }
        },
        "responses": {
          "201": {
            "description": ""
          }
        },
        "tags": [
          "certifications"
        ],
        "security": [
          {
            "access-token": []
          }
        ]
      }
    },
    "/certifications": {
      "get": {
        "operationId": "CertificationsController_list",
        "parameters": [],
        "responses": {
          "200": {
            "description": ""
          }
        },
        "tags": [
          "certifications"
        ],
        "security": [
          {
            "access-token": []
          }
        ]
      }
    },
    "/certifications/mark-expired": {
      "post": {
        "operationId": "CertificationsController_markExpired",
        "parameters": [],
        "responses": {
          "201": {
            "description": ""
          }
        },
        "tags": [
          "certifications"
        ],
        "security": [
          {
            "access-token": []
          }
        ]
      }
    },
    "/certifications/{id}/pdf": {
      "get": {
        "operationId": "CertificationsController_downloadPdf",
        "parameters": [
          {
            "name": "id",
            "required": true,
            "in": "path",
            "schema": {
              "type": "string"
            }
          },
          {
            "name": "lang",
            "required": true,
            "in": "query",
            "schema": {
              "type": "string"
            }
          }
        ],
        "responses": {
          "200": {
            "description": ""
          }
        },
        "tags": [
          "certifications"
        ],
        "security": [
          {
            "access-token": []
          }
        ]
      }
    },
    "/health": {
      "get": {
        "operationId": "HealthController_basic",
        "parameters": [],
        "responses": {
          "200": {
            "description": ""
          }
        }
      }
    },
    "/health/ready": {
      "get": {
        "operationId": "HealthController_ready",
        "parameters": [],
        "responses": {
          "200": {
            "description": ""
          }
        }
      }
    },
    "/ops/metrics": {
      "get": {
        "operationId": "OpsController_metricsSnapshot",
        "parameters": [],
        "responses": {
          "200": {
            "description": ""
          }
        },
        "tags": [
          "ops"
        ],
        "security": [
          {
            "access-token": []
          }
        ]
      }
    },
    "/ops/metrics/lti": {
      "get": {
        "operationId": "OpsController_ltiMetrics",
        "parameters": [],
        "responses": {
          "200": {
            "description": ""
          }
        },
        "tags": [
          "ops"
        ],
        "security": [
          {
            "access-token": []
          }
        ]
      }
    },
    "/ops/metrics/ai": {
      "get": {
        "operationId": "OpsController_aiMetrics",
        "parameters": [],
        "responses": {
          "200": {
            "description": ""
          }
        },
        "tags": [
          "ops"
        ],
        "security": [
          {
            "access-token": []
          }
        ]
      }
    },
    "/lti/tools": {
      "get": {
        "operationId": "LtiController_listTools",
        "parameters": [],
        "responses": {
          "200": {
            "description": ""
          }
        },
        "tags": [
          "lti"
        ],
        "security": [
          {
            "access-token": []
          }
        ]
      },
      "post": {
        "operationId": "LtiController_createTool",
        "parameters": [],
        "requestBody": {
          "required": true,
          "content": {
            "application/json": {
              "schema": {
                "$ref": "#/components/schemas/CreateLtiToolDto"
              }
            }
          }
        },
        "responses": {
          "201": {
            "description": ""
          }
        },
        "tags": [
          "lti"
        ],
        "security": [
          {
            "access-token": []
          }
        ]
      }
    },
    "/lti/tools/{id}": {
      "patch": {
        "operationId": "LtiController_updateTool",
        "parameters": [
          {
            "name": "id",
            "required": true,
            "in": "path",
            "schema": {
              "type": "string"
            }
          }
        ],
        "requestBody": {
          "required": true,
          "content": {
            "application/json": {
              "schema": {
                "$ref": "#/components/schemas/UpdateLtiToolDto"
              }
            }
          }
        },
        "responses": {
          "200": {
            "description": ""
          }
        },
        "tags": [
          "lti"
        ],
        "security": [
          {
            "access-token": []
          }
        ]
      }
    },
    "/lti/deployments": {
      "post": {
        "operationId": "LtiController_createDeployment",
        "parameters": [],
        "requestBody": {
          "required": true,
          "content": {
            "application/json": {
              "schema": {
                "$ref": "#/components/schemas/CreateLtiDeploymentDto"
              }
            }
          }
        },
        "responses": {
          "201": {
            "description": ""
          }
        },
        "tags": [
          "lti"
        ],
        "security": [
          {
            "access-token": []
          }
        ]
      }
    },
    "/lti/launch": {
      "post": {
        "operationId": "LtiController_recordLaunch",
        "parameters": [],
        "requestBody": {
          "required": true,
          "content": {
            "application/json": {
              "schema": {
                "$ref": "#/components/schemas/LtiLaunchDto"
              }
            }
          }
        },
        "responses": {
          "201": {
            "description": ""
          }
        },
        "tags": [
          "lti"
        ],
        "security": [
          {
            "access-token": []
          }
        ]
      }
    },
    "/lti/tools/{id}/deployments": {
      "get": {
        "operationId": "LtiController_deployments",
        "parameters": [
          {
            "name": "id",
            "required": true,
            "in": "path",
            "schema": {
              "type": "string"
            }
          }
        ],
        "responses": {
          "200": {
            "description": ""
          }
        },
        "tags": [
          "lti"
        ],
        "security": [
          {
            "access-token": []
          }
        ]
      }
    },
    "/ai/agents": {
      "get": {
        "operationId": "AiAgentsController_list",
        "parameters": [],
        "responses": {
          "200": {
            "description": ""
          }
        },
        "tags": [
          "ai"
        ],
        "security": [
          {
            "access-token": []
          }
        ]
      }
    },
    "/ai/agents/{id}/execute": {
      "post": {
        "operationId": "AiAgentsController_execute",
        "parameters": [
          {
            "name": "id",
            "required": true,
            "in": "path",
            "schema": {
              "type": "string"
            }
          }
        ],
        "responses": {
          "201": {
            "description": ""
          }
        },
        "tags": [
          "ai"
        ],
        "security": [
          {
            "access-token": []
          }
        ]
      }
    },
    "/ai/agents/{id}/logs": {
      "get": {
        "operationId": "AiAgentsController_logs",
        "parameters": [
          {
            "name": "id",
            "required": true,
            "in": "path",
            "schema": {
              "type": "string"
            }
          }
        ],
        "responses": {
          "200": {
            "description": ""
          }
        },
        "tags": [
          "ai"
        ],
        "security": [
          {
            "access-token": []
          }
        ]
      }
    },
    "/ai/agents/{id}/context": {
      "post": {
        "operationId": "AiAgentsController_context",
        "parameters": [
          {
            "name": "id",
            "required": true,
            "in": "path",
            "schema": {
              "type": "string"
            }
          }
        ],
        "requestBody": {
          "required": true,
          "content": {
            "application/json": {
              "schema": {
                "$ref": "#/components/schemas/AiContextDto"
              }
            }
          }
        },
        "responses": {
          "201": {
            "description": ""
          }
        },
        "tags": [
          "ai"
        ],
        "security": [
          {
            "access-token": []
          }
        ]
      }
    },
    "/ai/agents/{id}/feedback": {
      "post": {
        "operationId": "AiAgentsController_feedback",
        "parameters": [
          {
            "name": "id",
            "required": true,
            "in": "path",
            "schema": {
              "type": "string"
            }
          }
        ],
        "requestBody": {
          "required": true,
          "content": {
            "application/json": {
              "schema": {
                "$ref": "#/components/schemas/AiAgentFeedbackDto"
              }
            }
          }
        },
        "responses": {
          "201": {
            "description": ""
          }
        },
        "tags": [
          "ai"
        ],
        "security": [
          {
            "access-token": []
          }
        ]
      }
    },
    "/performance/snapshots": {
      "get": {
        "operationId": "PerformanceController_list",
        "parameters": [],
        "responses": {
          "200": {
            "description": ""
          }
        },
        "tags": [
          "performance"
        ],
        "security": [
          {
            "access-token": []
          }
        ]
      }
    },
    "/live/sessions": {
      "post": {
        "operationId": "LiveController_createSession",
        "parameters": [],
        "requestBody": {
          "required": true,
          "content": {
            "application/json": {
              "schema": {
                "$ref": "#/components/schemas/CreateLiveSessionDto"
              }
            }
          }
        },
        "responses": {
          "201": {
            "description": ""
          }
        },
        "tags": [
          "live"
        ],
        "security": [
          {
            "access-token": []
          }
        ]
      },
      "get": {
        "operationId": "LiveController_listSessions",
        "parameters": [
          {
            "name": "courseId",
            "required": true,
            "in": "query",
            "schema": {
              "type": "string"
            }
          }
        ],
        "responses": {
          "200": {
            "description": ""
          }
        },
        "tags": [
          "live"
        ],
        "security": [
          {
            "access-token": []
          }
        ]
      }
    },
    "/live/sessions/{id}": {
      "patch": {
        "operationId": "LiveController_updateSession",
        "parameters": [
          {
            "name": "id",
            "required": true,
            "in": "path",
            "schema": {
              "type": "string"
            }
          }
        ],
        "requestBody": {
          "required": true,
          "content": {
            "application/json": {
              "schema": {
                "$ref": "#/components/schemas/UpdateLiveSessionDto"
              }
            }
          }
        },
        "responses": {
          "200": {
            "description": ""
          }
        },
        "tags": [
          "live"
        ],
        "security": [
          {
            "access-token": []
          }
        ]
      }
    },
    "/live/sessions/{id}/participants": {
      "post": {
        "operationId": "LiveController_addParticipant",
        "parameters": [
          {
            "name": "id",
            "required": true,
            "in": "path",
            "schema": {
              "type": "string"
            }
          }
        ],
        "requestBody": {
          "required": true,
          "content": {
            "application/json": {
              "schema": {
                "$ref": "#/components/schemas/ParticipantStateDto"
              }
            }
          }
        },
        "responses": {
          "201": {
            "description": ""
          }
        },
        "tags": [
          "live"
        ],
        "security": [
          {
            "access-token": []
          }
        ]
      }
    },
    "/live/presentations": {
      "post": {
        "operationId": "LiveController_requestPresentation",
        "parameters": [],
        "requestBody": {
          "required": true,
          "content": {
            "application/json": {
              "schema": {
                "$ref": "#/components/schemas/PresentationRequestDto"
              }
            }
          }
        },
        "responses": {
          "201": {
            "description": ""
          }
        },
        "tags": [
          "live"
        ],
        "security": [
          {
            "access-token": []
          }
        ]
      }
    },
    "/live/presentations/respond": {
      "post": {
        "operationId": "LiveController_respondPresentation",
        "parameters": [],
        "requestBody": {
          "required": true,
          "content": {
            "application/json": {
              "schema": {
                "$ref": "#/components/schemas/PresentationResponseDto"
              }
            }
          }
        },
        "responses": {
          "201": {
            "description": ""
          }
        },
        "tags": [
          "live"
        ],
        "security": [
          {
            "access-token": []
          }
        ]
      }
    },
    "/live/messages": {
      "post": {
        "operationId": "LiveController_sendMessage",
        "parameters": [],
        "requestBody": {
          "required": true,
          "content": {
            "application/json": {
              "schema": {
                "$ref": "#/components/schemas/CommunicationDto"
              }
            }
          }
        },
        "responses": {
          "201": {
            "description": ""
          }
        },
        "tags": [
          "live"
        ],
        "security": [
          {
            "access-token": []
          }
        ]
      }
    },
    "/instructor-payments/me/summary": {
      "get": {
        "operationId": "InstructorPaymentsController_summary",
        "parameters": [],
        "responses": {
          "200": {
            "description": ""
          }
        },
        "tags": [
          "instructor-payments"
        ],
        "security": [
          {
            "access-token": []
          }
        ]
      }
    },
    "/instructor-payments/me/history": {
      "get": {
        "operationId": "InstructorPaymentsController_history",
        "parameters": [],
        "responses": {
          "200": {
            "description": ""
          }
        },
        "tags": [
          "instructor-payments"
        ],
        "security": [
          {
            "access-token": []
          }
        ]
      }
    },
    "/instructor-payments/admin/{instructorId}/history": {
      "get": {
        "operationId": "InstructorPaymentsController_adminHistory",
        "parameters": [
          {
            "name": "instructorId",
            "required": true,
            "in": "path",
            "schema": {
              "type": "string"
            }
          }
        ],
        "responses": {
          "200": {
            "description": ""
          }
        },
        "tags": [
          "instructor-payments"
        ],
        "security": [
          {
            "access-token": []
          }
        ]
      }
    },
    "/instructor-payments/admin/{instructorId}/summary": {
      "get": {
        "operationId": "InstructorPaymentsController_adminSummary",
        "parameters": [
          {
            "name": "instructorId",
            "required": true,
            "in": "path",
            "schema": {
              "type": "string"
            }
          }
        ],
        "responses": {
          "200": {
            "description": ""
          }
        },
        "tags": [
          "instructor-payments"
        ],
        "security": [
          {
            "access-token": []
          }
        ]
      }
    },
    "/instructor-payments/admin/{instructorId}/generate": {
      "post": {
        "operationId": "InstructorPaymentsController_generate",
        "parameters": [
          {
            "name": "instructorId",
            "required": true,
            "in": "path",
            "schema": {
              "type": "string"
            }
          }
        ],
        "requestBody": {
          "required": true,
          "content": {
            "application/json": {
              "schema": {
                "$ref": "#/components/schemas/InstructorPayoutRangeDto"
              }
            }
          }
        },
        "responses": {
          "201": {
            "description": ""
          }
        },
        "tags": [
          "instructor-payments"
        ],
        "security": [
          {
            "access-token": []
          }
        ]
      }
    },
    "/instructor-payments/admin/{paymentId}/pay": {
      "patch": {
        "operationId": "InstructorPaymentsController_markPaid",
        "parameters": [
          {
            "name": "paymentId",
            "required": true,
            "in": "path",
            "schema": {
              "type": "string"
            }
          }
        ],
        "requestBody": {
          "required": true,
          "content": {
            "application/json": {
              "schema": {
                "$ref": "#/components/schemas/MarkPayoutPaidDto"
              }
            }
          }
        },
        "responses": {
          "200": {
            "description": ""
          }
        },
        "tags": [
          "instructor-payments"
        ],
        "security": [
          {
            "access-token": []
          }
        ]
      }
    },
    "/volunteer-contents": {
      "post": {
        "operationId": "VolunteerContentController_create",
        "parameters": [],
        "requestBody": {
          "required": true,
          "content": {
            "application/json": {
              "schema": {
                "$ref": "#/components/schemas/CreateVolunteerContentDto"
              }
            }
          }
        },
        "responses": {
          "201": {
            "description": ""
          }
        },
        "tags": [
          "volunteer-contents"
        ],
        "security": [
          {
            "access-token": []
          }
        ]
      }
    },
    "/volunteer-contents/me": {
      "get": {
        "operationId": "VolunteerContentController_listMine",
        "parameters": [],
        "responses": {
          "200": {
            "description": ""
          }
        },
        "tags": [
          "volunteer-contents"
        ],
        "security": [
          {
            "access-token": []
          }
        ]
      }
    },
    "/volunteer-contents/{id}/feedback": {
      "post": {
        "operationId": "VolunteerContentController_submitFeedback",
        "parameters": [
          {
            "name": "id",
            "required": true,
            "in": "path",
            "schema": {
              "type": "string"
            }
          }
        ],
        "requestBody": {
          "required": true,
          "content": {
            "application/json": {
              "schema": {
                "$ref": "#/components/schemas/CreateVolunteerFeedbackDto"
              }
            }
          }
        },
        "responses": {
          "201": {
            "description": ""
          }
        },
        "tags": [
          "volunteer-contents"
        ],
        "security": [
          {
            "access-token": []
          }
        ]
      }
    },
    "/volunteer-contents/admin": {
      "get": {
        "operationId": "VolunteerContentController_adminList",
        "parameters": [],
        "responses": {
          "200": {
            "description": ""
          }
        },
        "tags": [
          "volunteer-contents"
        ],
        "security": [
          {
            "access-token": []
          }
        ]
      }
    },
    "/volunteer-contents/{id}/status": {
      "patch": {
        "operationId": "VolunteerContentController_updateStatus",
        "parameters": [
          {
            "name": "id",
            "required": true,
            "in": "path",
            "schema": {
              "type": "string"
            }
          }
        ],
        "requestBody": {
          "required": true,
          "content": {
            "application/json": {
              "schema": {
                "$ref": "#/components/schemas/UpdateVolunteerContentStatusDto"
              }
            }
          }
        },
        "responses": {
          "200": {
            "description": ""
          }
        },
        "tags": [
          "volunteer-contents"
        ],
        "security": [
          {
            "access-token": []
          }
        ]
      }
    },
    "/volunteer-contents/me/score": {
      "get": {
        "operationId": "VolunteerContentController_myScore",
        "parameters": [],
        "responses": {
          "200": {
            "description": ""
          }
        },
        "tags": [
          "volunteer-contents"
        ],
        "security": [
          {
            "access-token": []
          }
        ]
      }
    },
    "/volunteer-contents/admin/{instructorId}/scores": {
      "get": {
        "operationId": "VolunteerContentController_instructorScores",
        "parameters": [
          {
            "name": "instructorId",
            "required": true,
            "in": "path",
            "schema": {
              "type": "string"
            }
          }
        ],
        "responses": {
          "200": {
            "description": ""
          }
        },
        "tags": [
          "volunteer-contents"
        ],
        "security": [
          {
            "access-token": []
          }
        ]
      },
      "post": {
        "operationId": "VolunteerContentController_recordInstructorScores",
        "parameters": [
          {
            "name": "instructorId",
            "required": true,
            "in": "path",
            "schema": {
              "type": "string"
            }
          }
        ],
        "responses": {
          "201": {
            "description": ""
          }
        },
        "tags": [
          "volunteer-contents"
        ],
        "security": [
          {
            "access-token": []
          }
        ]
      }
    },
    "/volunteer-contents/admin/{instructorId}/score": {
      "get": {
        "operationId": "VolunteerContentController_instructorScore",
        "parameters": [
          {
            "name": "instructorId",
            "required": true,
            "in": "path",
            "schema": {
              "type": "string"
            }
          }
        ],
        "responses": {
          "200": {
            "description": ""
          }
        },
        "tags": [
          "volunteer-contents"
        ],
        "security": [
          {
            "access-token": []
          }
        ]
      }
    }
  },
  "info": {
    "title": "Atlasio API",
    "description": "Atlasio Kurumsal Uzaktan Eğitim API",
    "version": "0.2.0",
    "contact": {}
  },
  "tags": [],
  "servers": [],
  "components": {
    "securitySchemes": {
      "access-token": {
        "scheme": "bearer",
        "bearerFormat": "JWT",
        "type": "http",
        "in": "header"
      },
      "tenant": {
        "type": "apiKey",
        "in": "header",
        "name": "X-Tenant-ID"
      }
    },
    "schemas": {
      "RegisterDto": {
        "type": "object",
        "properties": {}
      },
      "LoginDto": {
        "type": "object",
        "properties": {}
      },
      "CreateCourseDto": {
        "type": "object",
        "properties": {}
      },
      "PublishCourseDto": {
        "type": "object",
        "properties": {}
      },
      "CreateScheduledReportDto": {
        "type": "object",
        "properties": {}
      },
      "UpdateScheduledReportDto": {
        "type": "object",
        "properties": {}
      },
      "CreateLessonDto": {
        "type": "object",
        "properties": {
          "title": {
            "type": "string",
            "example": "Giriş"
          },
          "order": {
            "type": "number",
            "example": 1
          },
          "content": {
            "type": "string",
            "example": "Hoş geldin!"
          },
          "isPreview": {
            "type": "boolean",
            "example": true
          },
          "videoUrl": {
            "type": "string",
            "example": "https://example.com/video.mp4"
          }
        },
        "required": [
          "title"
        ]
      },
      "CreateLearningPlanDto": {
        "type": "object",
        "properties": {}
      },
      "AddCourseToLearningPlanDto": {
        "type": "object",
        "properties": {}
      },
      "AssignLearningPlanDto": {
        "type": "object",
        "properties": {}
      },
      "IssueCertificationDto": {
        "type": "object",
        "properties": {}
      },
      "CreateLtiToolDto": {
        "type": "object",
        "properties": {}
      },
      "UpdateLtiToolDto": {
        "type": "object",
        "properties": {}
      },
      "CreateLtiDeploymentDto": {
        "type": "object",
        "properties": {}
      },
      "LtiLaunchDto": {
        "type": "object",
        "properties": {}
      },
      "AiContextDto": {
        "type": "object",
        "properties": {}
      },
      "AiAgentFeedbackDto": {
        "type": "object",
        "properties": {}
      },
      "CreateLiveSessionDto": {
        "type": "object",
        "properties": {}
      },
      "UpdateLiveSessionDto": {
        "type": "object",
        "properties": {}
      },
      "ParticipantStateDto": {
        "type": "object",
        "properties": {}
      },
      "PresentationRequestDto": {
        "type": "object",
        "properties": {}
      },
      "PresentationResponseDto": {
        "type": "object",
        "properties": {}
      },
      "CommunicationDto": {
        "type": "object",
        "properties": {}
      },
      "InstructorPayoutRangeDto": {
        "type": "object",
        "properties": {}
      },
      "MarkPayoutPaidDto": {
        "type": "object",
        "properties": {}
      },
      "CreateVolunteerContentDto": {
        "type": "object",
        "properties": {}
      },
      "CreateVolunteerFeedbackDto": {
        "type": "object",
        "properties": {}
      },
      "UpdateVolunteerContentStatusDto": {
        "type": "object",
        "properties": {}
      }
    }
  }
}